reddit_multimodal_crawler/__init__.py
reddit_multimodal_crawler/crawler.py
reddit_multimodal_crawler-1.3.2.dist-info/METADATA
reddit_multimodal_crawler-1.3.2.dist-info/WHEEL
reddit_multimodal_crawler-1.3.2.dist-info/top_level.txt
reddit_multimodal_crawler-1.3.2.dist-info/RECORD
