Metadata-Version: 2.1
Name: reddit-multimodal-crawler
Version: 1.3.2
Summary: A scraper which will scrape out multimedia data from reddit.
Home-page: https://github.com/aneesh-aparajit/reddit-crawler
Author: Aneesh Aparajit G
Author-email: aneeshaparajit.g2002@gmail.com
Keywords: web-scraping,webscraper,reddit,multimodal,datascience
Requires-Dist: praw
Requires-Dist: pandas
Requires-Dist: numpy
Requires-Dist: requests
Requires-Dist: bcrypt
Requires-Dist: nltk
